{
  "items": [

    { "key": "CP1-1", "value": "?????" },
    {"key": "CP1-1TXT","value": "Espera... Un momento... Eres tu! Te reconozco! No me lo puedo creer, pense que te habia perdido."},

    {"key": "CP1-2", "value": "Protagonista"},
    {"key": "CP1-2TXT", "value": "Eh... Como que me reconoces? Se puede saber quien eres?"},

    { "key": "CP1-3", "value": "?????" },
    {"key": "CP1-3TXT","value": "Ay... Claro... Perdona... Es normal que no me reconozcas..."},

    {"key": "CP1-4", "value": "Cientifico Johan"},
    {"key": "CP1-4TXT", "value": "Se que sonara dificil de creer pero soy Johan, tu creador... "},

    { "key": "CP1-5", "value": "Cientifico Johan" },
    { "key": "CP1-5TXT", "value": "Despues de que la Fundacion SEP atacara las instalaciones de la U.G.T donde trabajaba tuve que huir y no pude llevarte conmigo. Por eso no esperaba encontrarte." },

    { "key": "CP1-6.1", "value": "Tu eres el cientifico Marco entonces, como me habia dicho AURA" },
    { "key": "CP1-6.2", "value": "Asi que me abandonaste?" },
    { "key": "CP1-6.3", "value": "Alguien ataco el laboratorio donde me creaste?" },

    { "key": "CP1-6.1.1", "value": "Cientifico Johan" },
    { "key": "CP1-6.1.1TXT", "value": "Exacto! Asi que ya has conocido a AURA... Bien bien" },
    { "key": "CP1-6.1.2", "value": "Cientifico Johan" },
    { "key": "CP1-6.1.2TXT", "value": "Espero que te haya parecido agradable, estareis juntos por mucho tiempo" },

    { "key": "CP1-6.2.1", "value": "Cientifico Johan" },
    { "key": "CP1-6.2.1TXT", "value": "... Asi es... No pude ponerte en marcha antes de que atacaran y hui..." },
    { "key": "CP1-6.2.2", "value": "Cientifico Johan" },
    { "key": "CP1-6.2.2TXT", "value": "Hice algo despreciable... y nunca me perdonare por ello... tu eres la unica salvacion que tenemos y te abandone por miedo." },
    { "key": "CP1-6.2.3", "value": "Cientifico Johan" },
    { "key": "CP1-6.2.3TXT", "value": "Parece ser que de algun modo el programa de emergencia te dio la vida antes de que cedieran las instalaciones... Aun asi, te pido perdon..." },

    { "key": "CP1-6.3.1", "value": "Cientifico Johan" },
    { "key": "CP1-6.3.1TXT", "value": "... Me temo que si... Formas parte de algo grande hijo... de un proyecto capaz de salvarnos a todos" },

    { "key": "CP1-7", "value": "Cientifico Johan" },
    { "key": "CP1-7TXT", "value": "Tengo que pedirte algo dificil. Algo que solo puedes hacer tu." },

    { "key": "CP1-8", "value": "Cientifico Johan" },
    { "key": "CP1-8TXT", "value": "Necesito tu ayuda. Seguramente ya te habras dado cuenta pero tienes habilidades que se escapan a la comprension humana. Y con esos poderes podemos cambiarlo todo." },

    { "key": "CP1-9", "value": "Cientifico Johan" },
    { "key": "CP1-9TXT", "value": "Yo formo parte de la U.G.T, una organización que se enfrenta a la Fundación SEP, unos tiranos que han destruido el mundo." },

    { "key": "CP1-10", "value": "Cientifico Johan" },
    { "key": "CP1-10TXT", "value": "Esta fundacion ha alterado la gravedad del planeta y ha causado estragos por todas partes. Ademas, no planean detenerse." },

    { "key": "CP1-11", "value": "Protagonista" },
    { "key": "CP1-11TXT", "value": "Y que pretendes que haga yo?" },

    { "key": "CP1-12", "value": "Cientifico Johan" },
    { "key": "CP1-12TXT", "value": "Te cree con estas habilidades para arreglar el desastre que han hecho en la Tierra..." },

    { "key": "CP1-13", "value": "Cientifico Johan" },
    { "key": "CP1-13TXT", "value": "Espero que puedas ayudarnos... por favor... ahora tengo que contactar a Amelia, la lider de la U.G.T. Ella sabra que hacer ahora." },

    { "key": "CP1-14", "value": "Protagonista" },
    { "key": "CP1-14TXT", "value": "Cuanto tardaras? " },

    { "key": "CP1-15", "value": "Cientifico Johan" },
    { "key": "CP1-15TXT", "value": "Ten paciencia... Ve a ver a la gente del pueblo mientras esperas. Son buena gente... Me han tratado bien... Una pena que no pueda ayudarles mas..." },



    { "key": "CP2-1", "value": "Cientifico Johan" },
    {"key": "CP2-1TXT","value": "No he terminado aun... Lo siento..."},

    {"key": "CP2-2.1", "value": "De acuerdo, ningun problema"},
    {"key": "CP2-2.2", "value": "Aun no? Vaya"},

    { "key": "CP2-3", "value": "Cientifico Johan" },
    {"key": "CP2-3TXT","value": "Lo siento... Seguro que encuentras a alguien que te pueda entretener un rato..."},


    { "key": "CP3-1", "value": "Cientifico Johan" },
    {"key": "CP3-1TXT","value": "Vale... Ya he hablado con Amelia."},

    { "key": "CP3-2", "value": "GRAVIX" },
    {"key": "CP3-2TXT","value": "Que te ha dicho?"},

    { "key": "CP3-3", "value": "Cientifico Johan" },
    {"key": "CP3-3TXT","value": "Le he contado todo. Ha estado muy contenta. Hacia tiempo que no la escuchaba alegrarse asi... Bueno, que me distraigo."},

    { "key": "CP3-4", "value": "Cientifico Johan" },
    {"key": "CP3-4TXT","value": "Volviendo a lo importante. Amelia se encuentra en el pueblo de Icy Crest, que se encuentra en una zona gravitacional cercana. Quiere que vayas alli para hablar con ella."},

    { "key": "CP3-5", "value": "GRAVIX" },
    {"key": "CP3-5TXT","value": "Zona gravitacional?"},

    { "key": "CP3-6", "value": "Cientifico Johan" },
    {"key": "CP3-6TXT","value": "Es como llamamos a las zonas que afectadas de forma diferente por la gravedad."},

    { "key": "CP3-7", "value": "Cientifico Johan" },
    {"key": "CP3-7TXT","value": "Cuando la Fundación SEP se cargo el nucleo gravitacional de la Tierra hizo que tuviera efectos muy diferentes por el mundo."},
    
    { "key": "CP3-8", "value": "GRAVIX" },
    {"key": "CP3-8TXT","value": "Y que clase de efectos ha causado en Icy Crest?"},

    { "key": "CP3-9", "value": "Cientifico Johan" },
    {"key": "CP3-9TXT","value": "La Tierra se rompio y el fragmento donde se situa ese pueblo se alejo del nucleo, haciendolo la zona habitable mas fria del planeta."},

    { "key": "CP3-10", "value": "GRAVIX" },
    {"key": "CP3-10TXT","value": "Y por que no se mueven de zona? Suena extremadamente peligroso estar ahi."},

    { "key": "CP3-11", "value": "Cientifico Johan" },
    {"key": "CP3-11TXT","value": "Las conexiones entre zonas gravitacionales son increiblemente inestables. La mayoria de gente no sobrevive el viaje. Por suerte, tu no eres como la mayoria."},

    { "key": "CP3-12", "value": "Cientifico Johan" },
    {"key": "CP3-12TXT","value": "Estas listo?"},

    { "key": "CP3-13.1", "value": "Lo estoy." },
    {"key": "CP3-13.2","value": "Aun no."},

    { "key": "CP3-14", "value": "Cientifico Johan" },
    {"key": "CP3-14TXT","value": "Casi se me olvida! Por el camino pasarás por una de las instalaciones de la Fundación SEP. Encargate de recoger todas las piezas roboticas que encuentres."},

    { "key": "CP3-15", "value": "Cientifico Johan" },
    {"key": "CP3-15TXT","value": " Amelia me las ha pedido, asi que deben ser muy importantes, aunque no se para que sirven, ella ya te lo contara... Supongo."},




    { "key": "BP1-1", "value": "Beatrice" },
    {"key": "BP1-1TXT","value": "Buenos dIas! Que tenemos por aquI? Un visitante?"},

    { "key": "BP1-2.1", "value": "Algo asi..."},
    { "key": "BP1-2.2", "value": "Se podria decir que soy el hijo de Johan" },

    { "key": "BP1-2.1.1", "value": "Beatrice" },
    {"key": "BP1-2.1.1TXT","value": "No seas timido. Todo el mundo es bienvenido. Incluso los viajeros mas extravagantes"},

    { "key": "BP1-2.2.1", "value": "Beatrice" },
    {"key": "BP1-2.2.1TXT","value": "Claro. De donde iba a salir un robot parlante si no era de su laboratorio."},

    { "key": "BP1-2.2.2", "value": "Beatrice" },
    {"key": "BP1-2.2.2TXT","value": "Siempre me deja maravillada con los que es capaz de hacer. "},

    { "key": "BP1-2.2.3", "value": "Beatrice" },
    {"key": "BP1-2.2.3TXT","value": "No habla mucho pero nunca falta para ayudarme a arreglar las maquinas del campo. Estoy muy agradecida con el."},

    {"key": "BP1-3", "value": "Beatrice"},
    {"key": "BP1-3TXT", "value": "Que te parece si te ofrezco un pequeno trabajito?"},

    {"key": "BP1-4", "value": "Beatrice"},
    {"key": "BP1-4TXT", "value": "Un terremoto causado hace unos pocos dias ha dejado una sala abandonada cercana patas arriba. Y tenia pensado usarla como almacen para mis cultivos."},

    {"key": "BP1-5", "value": "Beatrice"},
    {"key": "BP1-5TXT", "value": "Si me ayudas a deshacerme de toda la chatarra te puedes quedar con lo que encuentres de valor. Ten en cuenta que es un edificio de antes de la Gran Fragmentacion, quien sabe lo que te puedes encontrar."},

    {"key": "BP1-6", "value": "Protagonista"},
    {"key": "BP1-6TXT", "value": "Que quieres decir antes de la Gran Fragmentacion?"},

    {"key": "BP1-7", "value": "Beatrice"},
    {"key": "BP1-7TXT", "value": "Ya sabes, el dia del colapso. Cuando la Fundación SEP rompió la Tierra en pedacitos."},

    {"key": "BP1-8", "value": "Beatrice"},
    {"key": "BP1-8TXT", "value": "Entonces que me dices? Me echaras una mano?"},

    { "key": "BP1-9.1", "value": "Lo siento, no tengo tiempo para eso."},
    { "key": "BP1-9.2", "value": "Claro que si." },



    { "key": "BP2-1", "value": "Beatrice"},
    { "key": "BP2-1TXT", "value": "Increible! Ha sido impresionante. Muchas gracias." },

    { "key": "BP2-2", "value": "Beatrice"},
    { "key": "BP2-2TXT", "value": "Espero que hayas encontrado algo de valor." },

    { "key": "BP2-3.1", "value": "La verdad es que no." },
    { "key": "BP2-3.2", "value": "Sorprendentemente si"},

    { "key": "BP2-3.1.1", "value": "Beatrice"},
    { "key": "BP2-3.1.1TXT", "value": "Vaya... Siento escuchar eso. Tendras que conformarte con mi agradecimiento entonces. Gracias." },

    { "key": "BP2-3.2.1", "value": "Beatrice"},
    { "key": "BP2-3.2.1TXT", "value": "Me alegro. Bueno, yo me tengo que poner a trabajar otra vez. Espero volver a vernos." },



    { "key": "BP3-1", "value": "Beatrice"},
    { "key": "BP3-1TXT", "value": "Tu de nuevo? Te has vuelto a plantear mi oferta?" },

    { "key": "BP3-2.1", "value": "No..." },
    { "key": "BP3-2.2", "value": "Me lo he pensado mejor. Te ayudare."},


    { "key": "BP3-2.1.1", "value": "Beatrice"},
    { "key": "BP3-2.1.1TXT", "value": "No la pueden culpar a una por intentarlo. *Se rie*" },

    { "key": "BP3-2.2.1", "value": "Beatrice"},
    { "key": "BP3-2.2.1TXT", "value": "Perfecto! Muchas gracias." },



    { "key": "BP4-1", "value": "Beatrice"},
    { "key": "BP4-1TXT", "value": "Mucha suerte con tus viajes-" },

    { "key": "BP4-2", "value": "Beatrice" },
    { "key": "BP4-2TXT", "value": "Cuida bien de Johan. Es algo timido pero es un cielo."},



    { "key": "DP1-1", "value": "Alcalde Dante"},
    { "key": "DP1-1TXT", "value": "..." },

    { "key": "DP1-2", "value": "GRAVIX"},
    { "key": "DP1-2TXT", "value": "Hola? buenos días?" },
    
    { "key": "DP1-3", "value": "Alcalde Dante"},
    { "key": "DP1-3TXT", "value": "Asi que tu eres el robot que ha salido de las instalaciones derruidas..." },

    { "key": "DP1-4.1", "value": "Asi es. Algún problema?"},
    { "key": "DP1-4.2", "value": "Correcto. Y casi no lo consigo." },

    { "key": "DP1-4.1.1", "value": "Alcalde Dante"},
    { "key": "DP1-4.1.1TXT", "value": "Eso esta por ver. Dependerá de ti." },

    { "key": "DP1-4.1.2", "value": "GRAVIX"},
    { "key": "DP1-4.1.2TXT", "value": "No vengo a causar problemas. Estoy con el cientifico Johan." },

    { "key": "DP1-4.1.3", "value": "Alcalde Dante"},
    { "key": "DP1-4.1.3TXT", "value": "Hm... Si tu lo dices. Soy el alcalde de Blossomvile, te tendré vigilado." },

    { "key": "DP1-4.1.4.1", "value": "Haz lo que quieras,"},
    { "key": "DP1-4.1.4.2", "value": "Entiendo tu desconfianza. Dejame demostrartelo. Hay algo que pueda hacer por ti?" },


    { "key": "DP1-4.2.1", "value": "Alcalde Dante"},
    { "key": "DP1-4.2.1TXT", "value": "Entiendo. Y que te tienes pensado hacer por mi pueblo ahora?" },

    { "key": "DP1-4.2.2", "value": "GRAVIX"},
    { "key": "DP1-4.2.2TXT", "value": "Por tu pueblo? Eres el alcalde?" },

    { "key": "DP1-4.2.3", "value": "Alcalde Dante"},
    { "key": "DP1-4.2.3TXT", "value": "Si, soy Dante, el alcalde de Blossomvile. O lo que queda de ella despues del ataque de la fundación SEP" },

    { "key": "DP1-4.2.4.1", "value": "Siento que no haya podido hacer nada al respecto. Hay algo con lo que te pueda ayudar?"},
    { "key": "DP1-4.2.4.2", "value": "Mucha suerte entonces. Nos vemos." },

    { "key": "DP1-5", "value": "Alcalde Dante"},
    { "key": "DP1-5TXT", "value": "Es una buena oportunidad para ver de que es capaz Johan con buenos recursos." },

    { "key": "DP1-6", "value": "Alcalde Dante"},
    { "key": "DP1-6TXT", "value": "Necesito que consigas una bobina estabilizadora. Ve a las ruinas de un antiguo edificio cerca de aqui y la encontraras." },



    { "key": "DP2-1", "value": "Alcalde Dante"},
    { "key": "DP2-1TXT", "value": "Veo que lo has conseguido. Me disculpo por dudar de ti." },

    { "key": "DP2-2", "value": "GRAVIX"},
    { "key": "DP2-2TXT", "value": "Todo solucionado entonces." },
    
    { "key": "DP2-3", "value": "Alcalde Dante"},
    { "key": "DP2-3TXT", "value": "La verdad es que solo era un prueba. Puedes quedarte la bobina como agradecimiento." },

    { "key": "DP2-4", "value": "Alcalde Dante"},
    { "key": "DP2-4TXT", "value": "Al fin y al cabo la has conseguido tu." },

    { "key": "DP2-5", "value": "GRAVIX"},
    {
      "key": "DP2-5TXT",
      "value": "Gracias."
    },

    { "key": "DP3-1", "value": "Alcalde Dante"},
    { "key": "DP3-1TXT", "value": "Mucho animo. Siendo una creación de Johan, te esperan grandes cosas" },

    { "key": "DP3-2", "value": "GRAVIX"},
    { "key": "DP3-2TXT", "value": "Gracias alcalde." },



    { "key": "DP4-1", "value": "Alcalde Dante"},
    { "key": "DP4-1TXT", "value": "Aun sigues por aqui? Que quieres forastero?" },

    { "key": "DP4-2.1", "value": "Nada nada. Mejor me voy ya."},
    { "key": "DP4-2.2", "value": "Hemos empezado con mal pie. Por que no me dices algo en lo que te pueda ayudar para hacerte cambiar de opinion?" },
    
    { "key": "DP4-3", "value": "Alcalde Dante"},
    { "key": "DP4-3TXT", "value": "Veamos, si que hay algo en lo que me puedes ayudar. Necesito que consigas una bobina estabilizadora. Ve a las ruinas de un antiguo edificio cerca de aqui y la encontraras." },




    { "key": "AP1-1", "value": "Amelia"},
    { "key": "AP1-1TXT", "value": "Por fin has llegado. A que se debe tu demora? No importa. No tenemos tiempo que perder." },

    { "key": "AP1-2", "value": "Amelia"},
    { "key": "AP1-2TXT", "value": "Tengo entendido que eres GRAVIX. Un placer conocerte por fin. Johan hablaba sobre lo crucial que serias para nuestra victoria." },

    { "key": "AP1-3", "value": "Amelia"},
    { "key": "AP1-3TXT", "value": "Has traido el artefacto robotico de las instalaciones de la Fundación SEP?" },

    { "key": "AP1-4", "value": "GRAVIX"},
    { "key": "AP1-4TXT", "value": "Un placer trabajar con usted. Claro, he encontrado esto." },

    { "key": "AP1-5", "value": "Amelia"},
    { "key": "AP1-5TXT", "value": "Perfecto. Es justo lo que necesitabamos." },

    { "key": "AP1-6.1", "value": "Que es esa pieza? Para que la necesitabas."},
    { "key": "AP1-6.2", "value": "Entonces. En que puedo ayudar ahora?" },

    { "key": "AP1-6.1.1", "value": "Amelia"},
    { "key": "AP1-6.1.1TXT", "value": "Te gusta hacer preguntas? Todo a su debido tiempo." },

    { "key": "AP1-6.1.2", "value": "Amelia"},
    { "key": "AP1-6.1.2TXT", "value": "Aunque me parece justo contraErtelo. Una buena recompensa para un buen trabajo. " },

    { "key": "AP1-6.1.3", "value": "Amelia"},
    { "key": "AP1-6.1.3TXT", "value": "Con este artefacto robOtico mejoraremos tus capacidades de control de gravedad temporalmente." },

    { "key": "AP1-6.1.4.1", "value": "Es eso posible? Puedo tener aun mas control?"},
    { "key": "AP1-6.1.4.2", "value": "De verdad me mejorareis con piezas de la Fundacion SEP?" },

    { "key": "AP1-6.1.4.1.1", "value": "Amelia"},
    { "key": "AP1-6.1.4.1.1TXT", "value": "Claro robot. Fuiste creado para rejuntar todas las piezas fragmentadas del planeta." },

    { "key": "AP1-6.1.4.1.2", "value": "GRAVIX"},
    { "key": "AP1-6.1.4.1.2TXT", "value": "Imposible. Eso es mucho mAs que mejorar mis capacidades" },

    { "key": "AP1-6.1.4.1.3", "value": "Amelia"},
    { "key": "AP1-6.1.4.1.3TXT", "value": "No dudes GRAVIX. Es tu propOsito. Para eso fuiste creado." },

    { "key": "AP1-6.1.4.1.4", "value": "GRAVIX"},
    { "key": "AP1-6.1.4.1.4TXT", "value": "Entonces toda el fracaso o el exito recaera sobre mi?" },

    { "key": "AP1-6.1.4.1.5", "value": "Amelia"},
    { "key": "AP1-6.1.4.1.5TXT", "value": "No te habia contado nada Johan? Ese hombre siempre ha sido inutil con las palabras. " },

    { "key": "AP1-6.1.4.1.6", "value": "Amelia"},
    { "key": "AP1-6.1.4.1.6TXT", "value": "Aunque nunca hubiesemos llegado tan lejos sin el." },

    { "key": "AP1-6.1.4.1.7", "value": "Amelia"},
    { "key": "AP1-6.1.4.1.7TXT", "value": "Ya me disculpare con el cuando todo termine." },

    { "key": "AP1-6.1.4.1.8", "value": "GRAVIX"},
    { "key": "AP1-6.1.4.1.8TXT", "value": "Disculparte? Por que dices eso?" },

    { "key": "AP1-6.1.4.1.9", "value": "Amelia"},
    { "key": "AP1-6.1.4.1.9TXT", "value": "Basta de preguntas. Vuelve mAs tarde. Tengo que preparar la siguiente parte del plan." },

    { "key": "AP1-6.1.4.2.1", "value": "Amelia"},
    { "key": "AP1-6.1.4.2.1TXT", "value": "Dudas de nuestros metodos? Haremos lo necesario para salvar a la humanidad. Incluso usar su tecnologia si es necesario" },

    { "key": "AP1-6.1.4.2.2", "value": "Amelia"},
    { "key": "AP1-6.1.4.2.2TXT", "value": "A mi tampoco me gusta depender de ellos. Aunque tiene su gracia que su propia tecnología les traiga su perdición." },

    { "key": "AP1-6.1.4.2.3", "value": "GRAVIX"},
    { "key": "AP1-6.1.4.2.3TXT", "value": "Y que hare con estas mejoras en mis habilidades." },

    { "key": "AP1-6.1.4.2.4", "value": "Amelia"},
    { "key": "AP1-6.1.4.2.4TXT", "value": "Tendras la tarea mas honorable de todas. Reunificar la Tierra. Atraer o alejar todos sus fragmentos a la altura necesaria" },

    { "key": "AP1-6.1.4.2.5", "value": "GRAVIX"},
    { "key": "AP1-6.1.4.2.5TXT", "value": "Pero... Como se supone que voy a hacer eso?" },

    { "key": "AP1-6.1.4.2.6", "value": "Amelia"},
    { "key": "AP1-6.1.4.2.6TXT", "value": "Ya basta de preguntas GRAVIX. ConfIa en tus lideres." },

    { "key": "AP1-6.1.4.2.7", "value": "Amelia"},
    { "key": "AP1-6.1.4.2.7TXT", "value": "Ven mas tarde. Necesito hacer unas preparaciones." },

    { "key": "AP1-6.2.1", "value": "Amelia"},
    { "key": "AP1-6.2.1TXT", "value": "Veo iniciativa. Gente con la que me gusta trabajar." },

    { "key": "AP1-6.2.2", "value": "Amelia"},
    { "key": "AP1-6.2.2TXT", "value": "Necesitamos otro artefacto robotico mas." },

    { "key": "AP1-6.2.3", "value": "Amelia"},
    { "key": "AP1-6.2.3TXT", "value": "Tengo que concretar para saber donde enviarte ahora. Asi que tardare unas horas." },

    { "key": "AP1-6.2.4", "value": "Amelia"},
    { "key": "AP1-6.2.4TXT", "value": "Una vez sepa su localizacion exacta conseguiras ese artefacto y junto al que ya tienes te los implantaras" },

    { "key": "AP1-6.2.5", "value": "GRAVIX"},
    { "key": "AP1-6.2.5TXT", "value": "COMO?" },

    { "key": "AP1-6.2.6", "value": "Amelia"},
    { "key": "AP1-6.2.6TXT", "value": "Son mejoras GRAVIX. El futuro es hoy. Si quieres colaborar, tienes que mejorar." },

    { "key": "AP1-6.2.7", "value": "Amelia"},
    { "key": "AP1-6.2.7TXT", "value": "Con la mejora seras capaz de muchas mas cosas de las que ni te imaginas." },

    { "key": "AP1-6.2.8", "value": "Amelia"},
    { "key": "AP1-6.2.8TXT", "value": "Demomento paciencia. Ayuda por el pueblo mientras trabajo." },


    { "key": "AP2-1", "value": "Amelia"},
    { "key": "AP2-1TXT", "value": "No te he llamado. Vuelve al pueblo. Es una orden" },


    { "key": "AP3-1", "value": "Amelia"},
    { "key": "AP3-1TXT", "value": "Bien. Justo a tiempo. Deja que te cuente que llevo haciendo todo este tiempo en el pueblo de Icy Crust." },

    { "key": "AP3-2", "value": "Amelia"},
    { "key": "AP3-2TXT", "value": "A travEs de esta zona tan inhOspita hemos trabajado para conseguir acceso a la zona gravitacional mas clave del planeta. " },

    { "key": "AP3-3", "value": "Amelia"},
    { "key": "AP3-3TXT", "value": "Desde aqui podemos llegar a la Iron Citadel. El pueblo mas cercano al nucleo." },

    { "key": "AP3-4", "value": "GRAVIX"},
    { "key": "AP3-4TXT", "value": "De que nos sirve que sea la zona mas cercana al nucleo?" },

    { "key": "AP3-5", "value": "Amelia"},
    { "key": "AP3-5TXT", "value": "Desde donde te crees que vas a tener que juntar el planeta GRAVIX." },

    { "key": "AP3-6", "value": "Amelia"},
    { "key": "AP3-6TXT", "value": "En el nucleo es donde encontraremos el artefacto que usa la Fundación SEP para controlar la gravedad. Si usamos ese artefacto junto a tus poderes mejorados podremos arreglar el planeta" },

    { "key": "AP3-7.1", "value": "Donde puedo encontrar el ultimo artefacto robotico entonces?"},
    { "key": "AP3-7.2", "value": "Aunque sea el punto mas cercano al nucleo. Como voy a conseguir llegar hasta ahi." },

    { "key": "AP3-7.1.1", "value": "Amelia"},
    { "key": "AP3-7.1.1TXT", "value": "Directo al grano. Perfecto. La buena noticia es que la Fundación SEP puede llegar a ser muy predecible. Sobre todo si conoces a esos bastardos tan bien como yo." },

    { "key": "AP3-7.2.1", "value": "Amelia"},
    { "key": "AP3-7.2.1TXT", "value": "En la Iron Citadel te encontraras con Carl. Mi compañero mas confiable y leal. El te dara la información que necesitas, ahora mismo no cuento con esos detalles." },

    { "key": "AP3-8", "value": "Amelia"},
    { "key": "AP3-8TXT", "value": "Llegaras a la Iron Citadel por una instalacion secreta de la Fundación SEP. Ahi encontraras el último artefacto y conseguiras llegar a tu destino." },

    { "key": "AP3-9", "value": "GRAVIX"},
    { "key": "AP3-9TXT", "value": "Entendido! Dare lo mejor de mi." },

    { "key": "AP3-10", "value": "Amelia"},
    { "key": "AP3-10TXT", "value": "Y recuerda. Instala las dos mejoras solo cuando llegues al centro del nucleo. Su efecto es temporal asi que no podemos permitirnos jugar a contrarreloj." },

    { "key": "AP3-11", "value": "Amelia"},
    { "key": "AP3-11TXT", "value": "Estas listo?" },

    { "key": "AP3-12.1", "value": "Lo estoy!"},
    { "key": "AP3-12.2", "value": "Aun no, espera un momento." },

    { "key": "AP3-12.1.1", "value": "Amelia"},
    { "key": "AP3-12.1.1TXT", "value": "Adelante GRAVIX. Ha sido un placer conocerte. No olvidare tus esfuerzos." },

    { "key": "AP4-1", "value": "Amelia"},
    { "key": "AP4-1TXT", "value": "Vamos! No hay tiempo que perder. Estas listo ya?" },

    { "key": "AP4-2.1", "value": "Si, ya lo estoy."},
    { "key": "AP4-2.2", "value": "De que nos sirve que sea la zona mas cercana al nucleo?" },

    { "key": "AP4-2.1.1", "value": "Amelia"},
    { "key": "AP4-2.1.1TXT", "value": "Animo! Dales su merecido por mi GRAVIX." },

    { "key": "AP4-2.2.1", "value": "Amelia"},
    { "key": "AP4-2.2.1TXT", "value": "Maldita sea! Cuanto piensas tardar." },




    { "key": "OP1-1", "value": "Olaf"},
    { "key": "OP1-1TXT", "value": "Woah! Que robot tan exotico. Nunca habia visto uno parecido." },

    { "key": "OP1-2", "value": "Olaf"},
    { "key": "OP1-2TXT", "value": "Yo me llamo Olaf. Te puedo tomar una foto?" },

    { "key": "OP1-3.1", "value": "Veo que has reconocido mi atractivo. Claro, hazme la foto"},
    { "key": "OP1-3.2", "value": "No gracias." },

    { "key": "OP1-3.1.1", "value": "Olaf"},
    { "key": "OP1-3.1.1TXT", "value": "Si si. Asi al natural sera perfecto." },

    { "key": "OP1-3.2.1", "value": "Olaf"},
    { "key": "OP1-3.2.1TXT", "value": "Vaya. Ya tengo fotos de toda la gente del pueblo y el paisaje es siempre el mismo. Que aburrido." },

    { "key": "OP1-4", "value": "Olaf"},
    { "key": "OP1-4TXT", "value": "Bueno, ignorando eso... Los robots sois muy fuertes verdad?" },

    { "key": "OP1-5", "value": "GRAVIX"},
    { "key": "OP1-5TXT", "value": "Se podria decir asi imagino." },


    { "key": "OP1-6", "value": "Olaf"},
    { "key": "OP1-6TXT", "value": "Bien bien. Entonces tengo un favor que pedirte." },

    { "key": "OP1-7.1", "value": "Claro, estare encantado de ayudar señor."},
    { "key": "OP1-7.2", "value": "Estoy un poco ocupado ahora no puedo." },

    { "key": "OP1-7.1.1", "value": "Olaf"},
    { "key": "OP1-7.1.1TXT", "value": "Perfecto perfecto. Te recompensare. Te dare mi tesoro familiar." },

    { "key": "OP1-7.2.1", "value": "Olaf"},
    { "key": "OP1-7.2.1TXT", "value": "Vaya vaya.  No pasa nada entonces. Me quedare mi tesoro para mi." },

    { "key": "OP1-7.2.2.1", "value": "Que clase de tesoro?"},
    { "key": "OP1-7.2.2.2", "value": "Una pena. Ya nos veremos señor." },

    { "key": "OP1-7.2.3", "value": "Olaf"},
    { "key": "OP1-7.2.3TXT", "value": "Secreto secreto. Pero si te puedo decir que es de lo más valioso para ti." },

    { "key": "OP1-7.2.4.1", "value": "Me lo he vuelto a plantear. Te ayudare."},
    { "key": "OP1-7.2.4.2", "value": "Sigo sin estar interesado. Gracias por la oferta." },

    { "key": "OP1-8", "value": "GRAVIX"},
    { "key": "OP1-8TXT", "value": "Entonces, que tengo que hacer?" },

    { "key": "OP1-9", "value": "Olaf"},
    { "key": "OP1-9TXT", "value": "Solo tienes que sacar de la zona del hielo una caja que perdi durante mi ultima mudanza. Yo estoy demasiado viejo para eso." },


    { "key": "OP2-1", "value": "Olaf"},
    { "key": "OP2-1TXT", "value": "Asi que te ha podido la avaricia eh! Vas a ayudarme ahora?" },

    { "key": "OP2-2.1", "value": "Voy a ayudarte."},
    { "key": "OP2-2.2", "value": "Sigo sin estar interesado." },


    { "key": "OP3-1", "value": "Olaf"},
    { "key": "OP3-1TXT", "value": "Muchas muchas gracias robot." },

    { "key": "OP3-2", "value": "GRAVIX"},
    { "key": "OP3-2TXT", "value": "Puedes llamarme GRAVIX" },

    { "key": "OP3-3", "value": "Olaf"},
    { "key": "OP3-3TXT", "value": "GRAVIX dices... Entonces mi tesoro te sera realmente util..." },

    { "key": "OP3-4", "value": "Olaf"},
    { "key": "OP3-4TXT", "value": "Toma. Te lo has ganado." },

    { "key": "OP3-5", "value": "GRAVIX"},
    { "key": "OP3-5TXT", "value": "Gracias. A ver que tesoro es..." },

    { "key": "OP3-6", "value": "Olaf"},
    { "key": "OP3-6TXT", "value": "Es un modulo de refrigeracion. Para que no pases calor. " },

    { "key": "OP3-7", "value": "GRAVIX"},
    { "key": "OP3-7TXT", "value": "... Señor Olaf... Soy un robot... No paso calor... Y mucho menos en Icy Crust" },

    { "key": "OP3-8", "value": "Olaf"},
    { "key": "OP3-8TXT", "value": "Y de maxima potencia ademas. De nada." },

    { "key": "OP3-9", "value": "GRAVIX"},
    { "key": "OP3-9TXT", "value": "Gracias supongo..." },

    { "key": "OP3-10", "value": "Olaf"},
    { "key": "OP3-10TXT", "value": "Ya veras como te sera util!" },


    { "key": "OP4-1", "value": "Olaf"},
    { "key": "OP4-1TXT", "value": "Ya no tengo mas tesoros. Ve con cuidado o esa avaricia te consumira!" },

    
    { "key": "LP1-1", "value": "Leorio"},
    { "key": "LP1-1TXT", "value": "Eh! Tu! No eres de por aqui verdad?" },

    { "key": "LP1-2", "value": "Leorio"},
    { "key": "LP1-2TXT", "value": "Me llamo Leorio. No seras por casualidad un comerciante?" },
    
    { "key": "LP1-3.1", "value": "Me temo que no. Trabajo con Amelia."},
    { "key": "LP1-3.2", "value": "No lo soy señor. Pero si puedo ayudarte con algo. Solo pidelo." },

    { "key": "LP1-3.1.1", "value": "Leorio"},
    { "key": "LP1-3.1.1TXT", "value": "Otro experimento de la U.G.T? Veo que no saben cuando rendirse." },

    { "key": "LP1-3.1.2", "value": "GRAVIX"},
    { "key": "LP1-3.1.2TXT", "value": "Rendirse? Estan intentando salvar el planeta. Preferirias que no lo hiciesen?" },

    { "key": "LP1-3.1.3", "value": "Leorio"},
    { "key": "LP1-3.1.3TXT", "value": "No me malinterpretes. Aprecio sus esfuerzos por ayudar a la gente y dar esperanza." },

    { "key": "LP1-3.1.4", "value": "Leorio"},
    { "key": "LP1-3.1.4TXT", "value": "Pero hay que admitir que es obvio que este castigo divino no lo podemos solucionar los simples mortales." },   

    { "key": "LP1-3.2.1", "value": "Leorio"},
    { "key": "LP1-3.2.1TXT", "value": "La verdad es que el pueblo esta pasando frio. Las maquinas cada vez fallan mas" },

    { "key": "LP1-3.2.2", "value": "GRAVIX"},
    { "key": "LP1-3.2.2TXT", "value": "Como electricista del pueblo he tenido que reducir la cantidad de energia que producen para que no exploten ni falle la maquinaria." },

    { "key": "LP1-3.2.3", "value": "Leorio"},
    { "key": "LP1-3.2.3TXT", "value": "Necesito una bobina estabilizadora o los enfermos no pasaran el invierno. Sabes como conseguir alguna?" },

    { "key": "LP1-3.2.4.1", "value": "De hecho, yo tengo una. Si realmente la necesitáis tanto. Os la entrego."},
    { "key": "LP1-3.2.4.2", "value": "Me temo que no. Lo siento"},

    { "key": "LP1-3.2.4.2.1", "value": "Leorio"},
    { "key": "LP1-3.2.4.2.1TXT", "value": "Era de esperar. Esta claro que esto es un castigo divino, no hay nada que nosotros podamos hacer." },

    { "key": "LP1-3.1.5.1", "value": "Supongo que es una manera de verlo."},
    { "key": "LP1-3.1.5.2", "value": "No todo esta perdido Leorio. Confie en mi." },
    { "key": "LP1-3.1.5.3", "value": "Soy GRAVIX, un robot capaz de controlar la gravedad. No soy un simple mortal." },

    { "key": "LP1-3.1.5.1.1", "value": "Leorio"},
    { "key": "LP1-3.1.5.1.1TXT", "value": "Lo es. Y aunque ya llega el fin. Preferiria no pasar mis ultimos días congelado. No tendras una bobina estabilizadora no?" },

    { "key": "LP1-3.1.5.2.1", "value": "Leorio"},
    { "key": "LP1-3.1.5.2.1TXT", "value": "Las palabras se las lleva el viento amigo. Aunque agradezco el intento." },

    { "key": "LP1-3.1.5.2.2", "value": "Leorio"},
    { "key": "LP1-3.1.5.2.2TXT", "value": "Por cierto, no tendras por casualidad una bobina estabilizadora?" },

    { "key": "LP1-3.1.5.2.3", "value": "Leorio"},
    { "key": "LP1-3.1.5.2.3TXT", "value": "Con ella podre aumentar la capacidad energetica del pueblo. Y le daria más calor a todas las casas." },

    { "key": "LP1-3.1.5.3.1", "value": "Leorio"},
    { "key": "LP1-3.1.5.3.1TXT", "value": "Lo que usted diga. No tendrá el poderoso GRAVIX una bobina estabilizadora para un pobre anciano?" },

    { "key": "LP1-3.1.5.3.2", "value": "Leorio"},
    { "key": "LP1-3.1.5.3.2TXT", "value": "Con ella podre aumentar la capacidad energetica del pueblo. Y le daria mas calor a todas las casas." },

    { "key": "LP1-3.1.6.1", "value": "No, no tengo ninguna"},
    { "key": "LP1-3.1.6.2", "value": "Claro. Aquí tienes. Usala bien." },

    { "key": "LP1-3.1.6.1.1", "value": "Leorio"},
    { "key": "LP1-3.1.6.1.1TXT", "value": "Y luego esperan que confie en que salvaran al mundo. No pueden ni evitar que un anciano se congele" },

    { "key": "LP1-4", "value": "Leorio"},
    { "key": "LP1-4TXT", "value": "Bendito seas! Podre volver a dar corriente completa a todo a mi casa. Cuanto debe hacer que no conecto mi reproductor de música." },

    { "key": "LP1-5", "value": "Leorio"},
    { "key": "LP1-5TXT", "value": "Y al pueblo entero tambien le ira bien claro." },



    
    { "key": "LP2-1", "value": "Leorio"},
    { "key": "LP2-1TXT", "value": "Que tal amigo? Cuando quieras escuchar un poco de musica eres bienvenido por aqui." },

    { "key": "LP2-2", "value": "Leorio"},
    { "key": "LP2-2TXT", "value": "Tambien tengo chocolate caliente. Pero no se si los robots podeis tomarlo asi que mejor me lo quedo yo" },
    
    { "key": "LP2-3", "value": "GRAVIX"},
    { "key": "LP2-3TXT", "value": "Ningún problema Leorio. Ha sido un placer ayudar." },


    { "key": "LP3-1", "value": "Leorio"},
    { "key": "LP3-1TXT", "value": "Bueno, en el poco probable caso de que encuentres una bobina. Hazmelo saber." },

    { "key": "LP3-2.1", "value": "De hecho. Toma."},
    { "key": "LP3-2.2", "value": "Te lo hare saber." },


    { "key": "LP4-1", "value": "Leorio"},
    { "key": "LP4-1TXT", "value": "Eh! Tú! No eres de por aqui verdad?" },

    { "key": "LP4-2", "value": "Leorio"},
    { "key": "LP4-2TXT", "value": "Me llamo Leorio. No seras por casualidad un comerciante?" },
    
    { "key": "LP4-3.1", "value": "No, lo siento. Solo estoy de paso."},
    { "key": "LP4-3.2", "value": "Estoy trabajando con Amelia. Si hay algo con lo que pueda ayudar." },

    { "key": "LP4-3.1.1", "value": "Leorio"},
    { "key": "LP4-3.1.1TXT", "value": "Vaya... El castigo de Dios es de verdad es inesquivable." },

    { "key": "LP4-3.2.1", "value": "Leorio"},
    { "key": "LP4-3.2.1TXT", "value": "Incluso los robots teneis esperanza de conseguir algo trabajando con Amelia..." },

    { "key": "LP4-4", "value": "GRAVIX"},
    { "key": "LP4-4TXT", "value": "Que dices señor? Aun hay esperanza." },

    { "key": "LP4-5", "value": "Leorio"},
    { "key": "LP4-5TXT", "value": "Te crees algún tipo de mesías robot? Demuéstramelo." },

    { "key": "LP4-7", "value": "GRAVIX"},
    { "key": "LP4-7TXT", "value": "No..." },

    { "key": "LP4-6", "value": "Leorio"},
    { "key": "LP4-6TXT", "value": "Si tanta esperanza quieres que tenga dame lo que necesito para sobrevivir este invierno. Tienes una bobina estabilizadora?." },

    { "key": "LP4-8", "value": "Leorio"},
    { "key": "LP4-8TXT", "value": "Lo que pensaba" },

    { "key": "LP5-1", "value": "Leorio"},
    { "key": "LP5-1TXT", "value": "Déjame en paz. Tengo muchas cosas que hacer." },


    { "key": "C-1", "value": "Carl"},
    { "key": "C-1TXT", "value": "Ey! Aquí, soy Carl, ven conmigo." },

    { "key": "C-2", "value": "GRAVIX"},
    { "key": "C-2TXT", "value": "Amelia me dijo que te buscara, no pensaba que me fueses a encontrar tan rapido." },
  
    { "key": "C-3", "value": "Carl"},
    { "key": "C-3TXT", "value": "Que te esperabas del agente de la UGT más cercano a la Fundación SEP. " },

    { "key": "C-4", "value": "Carl"},
    { "key": "C-4TXT", "value": "Tu debes de ser GRAVIX por lo que tengo entendido." },

    { "key": "C-5", "value": "GRAVIX"},
    { "key": "C-5TXT", "value": "Asi es. " },

    { "key": "C-6", "value": "Carl"},
    { "key": "C-6TXT", "value": "Has conseguido las dos mejoras imagino. Ahora solo hace falta llevarte hasta el nucleo." },

    { "key": "C-7.1", "value": "Estamos en el sitio más importante de la Fundación SEP. No estara altamente protegido?"},
    { "key": "C-7.2", "value": "Que tendre que hacer dentro?" },

    { "key": "C-7.1.1", "value": "Carl"},
    { "key": "C-7.1.1TXT", "value": "Dudas amigo mio? Eso es lo que he estado preparando yo todo este tiempo." },

    { "key": "C-7.1.2", "value": "Carl"},
    { "key": "C-7.1.2TXT", "value": "Tengo una ruta que evitara que nos encontremos con nadie. Aunque tendras que ir tu solo, es demasiado peligroso para mi." },

    { "key": "C-7.1.3", "value": "GRAVIX"},
    { "key": "C-7.1.3TXT", "value": "Y para mi no lo será?" },

    { "key": "C-7.1.4", "value": "Carl"},
    { "key": "C-7.1.4TXT", "value": "Por favor GRAVIX, tu estas fabricado para aguantar la presión del nucleo. Yo no." },

    { "key": "C-7.1.5", "value": "Carl"},
    { "key": "C-7.1.5TXT", "value": "No te preocupes. Todo saldra bien, ya estamos en el ultimo paso para recuperar la Tierra." },

    { "key": "C-7.1.6", "value": "Carl"},
    { "key": "C-7.1.6TXT", "value": "Si sales antes de que se haga de noche te preparare uno de mis famosos estofados." },

    { "key": "C-7.1.7.1", "value": "Soy un robot, no puedo comer."},
    { "key": "C-7.1.7.2", "value": "Famosos estofados? No había oido hablar de ellos." },

    { "key": "C-7.1.7.1.1", "value": "Carl"},
    { "key": "C-7.1.7.1.1TXT", "value": "Que tacaño fue Johan. Pudo conseguir la tecnologia para que tuvieras consciencia y controlases la gravedad pero no podia ponerte papilas gustativas." },

    { "key": "C-7.1.7.2.1", "value": "Carl"},
    { "key": "C-7.1.7.2.1TXT", "value": "Como que no? No te menciono nada Amelia? Le absorbe demasiado el trabajo hasta para pensar en su comida favorita." },

    { "key": "C-7.1.8", "value": "GRAVIX"},
    { "key": "C-7.1.8TXT", "value": "No estas nervioso?" },

    { "key": "C-7.1.9", "value": "Carl"},
    { "key": "C-7.1.9TXT", "value": "Supongo que un poco. Pero siempre he confiado en que llegaría el día en que todo se solucionaría. " },

    { "key": "C-7.1.10", "value": "Carl"},
    { "key": "C-7.1.10TXT", "value": "Bueno, estes preparado o no. Es ahora o nunca. Vamos!" },

    { "key": "C-7.1.11", "value": "GRAVIX"},
    { "key": "C-7.1.11TXT", "value": "Si!" },


    { "key": "C-7.2.1", "value": "Carl"},
    { "key": "C-7.2.1TXT", "value": "Vale. Por lo que me ha contado Amelia tendrás que conectarte al artefacto que esté controlando el nucleo." },

    { "key": "C-7.2.2", "value": "Carl"},
    { "key": "C-7.2.2TXT", "value": "Entonces, junto a las mejoras que te pondrás deberías poder usar tus poderes a escala planetaria." },

    { "key": "C-7.2.3", "value": "Carl"},
    { "key": "C-7.2.3TXT", "value": "Como funcionan tus habilidades ya es cosa tuya. Usas una palabra clave como Avada Kedavra o que?" },

    { "key": "C-7.2.4.1", "value": "Es un poco más complejo que eso..."},
    { "key": "C-7.2.4.2", "value": "Yo digo Avada Kedavra  y  sucede la magia." },

    { "key": "C-7.2.4.1.1", "value": "Carl"},
    { "key": "C-7.2.4.1.1TXT", "value": "Me lo imaginaba..." },

    { "key": "C-7.2.4.2.1", "value": "Carl"},
    { "key": "C-7.2.4.2.1TXT", "value": "Si hombre! No me tomes el pelo JA JA." },

    { "key": "C-7.2.5", "value": "GRAVIX"},
    { "key": "C-7.2.5TXT", "value": "Cuando empezamos la misión?" },

    { "key": "C-7.2.6", "value": "Carl"},
    { "key": "C-7.2.6TXT", "value": "De hecho, ahora mismo. Te guiaré hasta una entrada secundaria." },

    { "key": "C-7.2.7", "value": "Carl"},
    { "key": "C-7.2.7TXT", "value": "Desde ahí tendrás acceso al núcleo. Yo cubriré la retirada." },

    { "key": "C-7.2.8", "value": "GRAVIX"},
    { "key": "C-7.2.8TXT", "value": "Vamos ya entonces?" },

    { "key": "C-7.2.9", "value": "Carl"},
    { "key": "C-7.2.9TXT", "value": "Efectivamente GRAVIX. No hay tiempo que perder. Somos la esperanza de la humanidad." },








    { "key": "A1-1", "value": "AURA"},
    { "key": "A1-1TXT", "value": "Que ilusión! Hemos conocido a nuestro creador. Que te ha parecido?" },

    { "key": "A1-2.1", "value": "Parece una buena persona. Eso me tranquiliza."},
    { "key": "A1-2.2", "value": "No me gusta. Me esperaba a alguien mejor." },

    { "key": "A1-2.1.1", "value": "AURA"},
    { "key": "A1-2.1.1TXT", "value": "Verdad que sí. Y además nos ha contado un montón de cosas interesantes." },

    { "key": "A1-2.2.1", "value": "AURA"},
    { "key": "A1-2.2.1TXT", "value": "No seas así. Parece que se esfuerza mucho en ayudar a la gente." },

    { "key": "A1-3", "value": "AURA"},
    { "key": "A1-3TXT", "value": "Deberíamos ayudarle a derrocar la Fundación SEP. Esa gente sí es maligna." },

    { "key": "A1-4.1", "value": "Claro. Hay que hacer lo que podamos para cumplir nuestro proposito."},
    { "key": "A1-4.2", "value": "Sí tu lo dices no tengo más remedio." },

    { "key": "A1-4.1.1", "value": "AURA"},
    { "key": "A1-4.1.1TXT", "value": "Exacto. Hay que cumplir con las expectativas de Johan." },

    { "key": "A1-4.2.1", "value": "AURA"},
    { "key": "A1-4.2.1TXT", "value": "Vamos... Sé más positivo!" },

    { "key": "A1-5", "value": "AURA"},
    { "key": "A1-5TXT", "value": "Empecemos por ver si alguien en Blossomvile necesita nuestra ayuda." },



    { "key": "A2-1", "value": "AURA"},
    { "key": "A2-1TXT", "value": "Increíble. Beatrice no exageraba cuando decía que este edificio es de antes de la Gran Fragmentación." },

    { "key": "A2-2", "value": "AURA"},
    { "key": "A2-2TXT", "value": "Mira esa pieza de ahí. Es una tarjeta de memoria. Cógela para que la analice." },

    { "key": "A2-3", "value": "GRAVIX"},
    { "key": "A2-3TXT", "value": "¿Tu crees que habrá algo interesante ahí dentro? Quizá solo es una base de datos inútil antigua." },

    { "key": "A2-4", "value": "AURA"},
    { "key": "A2-4TXT", "value": "¿Donde esta tu espíritu aventurero? Voy a analizarla igual..." },

    { "key": "A2-5", "value": "AURA"},
    { "key": "A2-5TXT", "value": "No te lo vas a creer GRAVIX. Es información de la Fundación SEP." },

    { "key": "A2-6", "value": "GRAVIX"},
    { "key": "A2-6TXT", "value": "¿Qué? ¿Y qué información has encontrado?" },

    { "key": "A2-7", "value": "AURA"},
    { "key": "A2-7TXT", "value": "Hablan sobre la Nucelomita y de como conseguirla." },

    { "key": "A2-8.1", "value": "Vaya... ¿Eso no es ningún misterio hoy en día no?"},
    { "key": "A2-8.2", "value": "¿Ahora podremos conseguir más metal para la UGT no?" },

    { "key": "A2-8.1.1", "value": "AURA"},
    { "key": "A2-8.1.1TXT", "value": "Eso no es lo interesante GRAVIX. Es la fecha. Estos documentos datan de mucho antes de la Gran Fragmentación." },

    { "key": "A2-8.2.1", "value": "AURA"},
    { "key": "A2-8.2.1TXT", "value": "La Nucleomita se encuentra en el centro de la Tierra... Eso ya lo sabe la UGT. Lo importante es la fecha." },

    { "key": "A2-8.1.2", "value": "AURA"},
    { "key": "A2-8.1.2TXT", "value": "Son documentos de la Era Voraz. Cuando la humanidad estaba en su auge. No deberían ni existir teorías sobre ese metal en ese entonces." },

    { "key": "A2-8.2.2", "value": "AURA"},
    { "key": "A2-8.2.2TXT", "value": "Son documentos de la Era Voraz. Cuando la humanidad estaba en su auge. No deberían ni existir teorías sobre ese metal en ese entonces." },

    { "key": "A2-8.1.3", "value": "AURA"},
    { "key": "A2-8.1.3TXT", "value": "Hay algo de la Fundación SEP que se le escapa incluso a la UGT. Muy curioso." },

    { "key": "A2-8.2.3", "value": "AURA"},
    { "key": "A2-8.2.3TXT", "value": "La Fundación SEP  tenia conocimiento que no debería ser descubierto por almenos otros 400 años. No tiene ningún sentido." },



    { "key": "A3-1", "value": "AURA"},
    { "key": "A3-1TXT", "value": "Que imponente es la líder de la UGT. No esperaba menos." },

    { "key": "A3-2.1", "value": "Quizá un poco borde."},
    { "key": "A3-2.2", "value": "Parece una líder respetable." },

    { "key": "A3-2.1.1", "value": "AURA"},
    { "key": "A3-2.1.1TXT", "value": "Un poco. Pero tiene buenas intenciones." },

    { "key": "A3-2.2.1", "value": "AURA"},
    { "key": "A3-2.2.1TXT", "value": "¡Sí! La UGT esta en buenas manos." },

    { "key": "A3-2.1.2", "value": "AURA"},
    { "key": "A3-2.1.2TXT", "value": "Aunque si te soy sincera. Me preocupan las mejoras que quiere que utilicemos. " },

    { "key": "A3-2.2.2", "value": "AURA"},
    { "key": "A3-2.2.2TXT", "value": "Aunque parece que lleva una carga muy grande encima. A ver si podemos ayudar a la gente del pueblo. Así se podrá relajar un poco." },

    { "key": "A3-2.1.3", "value": "AURA"},
    { "key": "A3-2.1.3TXT", "value": "No tengo información sobre estas mejoras en mi sistema. Parece que Johan no las tuvo en cuenta cuando nos creo." },



    { "key": "A4-1", "value": "AURA"},
    { "key": "A4-1TXT", "value": "¡Mira! Ya esta haciendo efecto las calefacciones alrededor del pueblo. Se deshace la nieve." },

    { "key": "A4-2", "value": "GRAVIX"},
    { "key": "A4-2TXT", "value": "Impresionante lo que puede hacer ese viejo cascarrabias cuando se lo propone." },

    { "key": "A4-3", "value": "AURA"},
    { "key": "A4-3TXT", "value": "No seas así... Aunque a mi también me preocupaba que no se quedase toda la energía para él." },

    { "key": "A4-4", "value": "GRAVIX"},
    { "key": "A4-4TXT", "value": "Mira eso de allí. La nieve cubría ese aparato. Esta iluminado, quizá aún funciona. " },

    { "key": "A4-5", "value": "AURA"},
    { "key": "A4-5TXT", "value": "Es un banco de memoria. Y parece muy antiguo. ¡Déjame escanearlo! ¡Seguro que tiene algo interesante!" },

    { "key": "A4-6.1", "value": "Claro. Que podría salir mal."},
    { "key": "A4-6.2", "value": "No hace falta. Tenemos prisa."},

    { "key": "A4-6.1.1", "value": "AURA"},
    { "key": "A4-6.1.1TXT", "value": "¡Bien! ¡Gracias! A ver que información extraemos..." },

    { "key": "A4-6.2.1", "value": "AURA"},
    { "key": "A4-6.2.1TXT", "value": "A veces eres un poco aburrido. Deberías hacerme más caso." },

    { "key": "A4-6.1.2", "value": "AURA"},
    { "key": "A4-6.1.2TXT", "value": "Esta encriptado. Tiene que ser información importante entonces." },

    { "key": "A4-6.1.3", "value": "AURA"},
    { "key": "A4-6.1.3TXT", "value": "Es de la Fundación SEP. Parece que esto antiguamente era una de sus bases." },

    { "key": "A4-6.1.4", "value": "GRAVIX"},
    { "key": "A4-6.1.4TXT", "value": "Eso explicaría porque la han dejado la zona prácticamente inhabitable y por que la líder de la UGT esta aquí." },

    { "key": "A4-6.1.5", "value": "AURA"},
    { "key": "A4-6.1.5TXT", "value": "Tienes razón. Pero escúchame. Aquí hay una base de datos sobre varios planetas." },

    { "key": "A4-6.1.6", "value": "GRAVIX"},
    { "key": "A4-6.1.6TXT", "value": "No lo entiendo." },

    { "key": "A4-6.1.7", "value": "AURA"},
    { "key": "A4-6.1.7TXT", "value": "Hay datos de dos planetas casi iguales. Y uno de ellos es la Tierra... La única diferencia es la cantidad de Nucleomita del núcleo." },

    { "key": "A4-6.1.8", "value": "GRAVIX"},
    { "key": "A4-6.1.8TXT", "value": "Eso significa que...  La Fundación SEP... No son de la Tierra..." },

    { "key": "A4-6.1.9", "value": "AURA"},
    { "key": "A4-6.1.9TXT", "value": "¡Son de otro mundo! ¡Y vienen a por la Nucelomita!" },

    { "key": "A4-6.1.10", "value": "GRAVIX"},
    { "key": "A4-6.1.10TXT", "value": "Eso seria una locura... " },

    { "key": "A4-6.1.11", "value": "AURA"},
    { "key": "A4-6.1.11TXT", "value": "¿Lo es? Tendría sentido. A lo mejor su mundo está como el nuestro e intentan arreglarlo. Eso sí, sacrificándonos a nosotros." },

    { "key": "A4-6.1.12", "value": "GRAVIX"},
    { "key": "A4-6.1.12TXT", "value": "Más motivos para seguir con el plan de Amelia." },



    { "key": "A5-1", "value": "AURA"},
    { "key": "A5-1TXT", "value": "¿Estas listo GRAVIX? Confío en ti, lo lograremos." },

    { "key": "A5-2", "value": "GRAVIX"},
    { "key": "A5-2TXT", "value": "Allá vamos... Ya no hay vuelta atrás..." },




    { "key": "A6-1", "value": "AURA"},
    { "key": "A6-1TXT", "value": "Hemos llegado. El núcleo de la Tierra..." },

    { "key": "A6-2", "value": "GRAVIX"},
    { "key": "A6-2TXT", "value": "Eso parece... Ahora solo queda hacer el esfuerzo final." },

    { "key": "A6-3", "value": "AURA"},
    { "key": "A6-3TXT", "value": "Todo esto a nuestro alrededor es Nucleomita refinada." },

    { "key": "A6-4", "value": "GRAVIX"},
    { "key": "A6-4TXT", "value": "Estas grandes cantidades son lo que mantendria estable la gravedad del planeta si no fuera por la Fundación SEP." },

    { "key": "A6-5", "value": "AURA"},
    { "key": "A6-5TXT", "value": "Así es. Pero eso va a cambiar muy rápido. Mira." },

    { "key": "A6-6", "value": "AURA"},
    { "key": "A6-6TXT", "value": "Esa parece la consola principal de la máquina que controla el núcleo." },

    { "key": "A6-7", "value": "GRAVIX"},
    { "key": "A6-7TXT", "value": "Me conectaré a esto..." },

    { "key": "A6-8", "value": "GRAVIX"},
    { "key": "A6-8TXT", "value": "Y ahora añadiré las mejoras como me dijo Amelia..." },

    { "key": "A6-9", "value": "AURA"},
    { "key": "A6-9TXT", "value": "Ve con cuidado." },

    { "key": "A6-10", "value": "GRAVIX"},
    { "key": "A6-10TXT", "value": "Ya esta. Conectado." },

    { "key": "A6-11", "value": "AURA"},
    { "key": "A6-11TXT", "value": "¿Estas listo GRAVIX?" },

    { "key": "A6-12.1", "value": "Sí. Fui creado para esto. Este es mi proposito."},
    { "key": "A6-12.2", "value": "Noto el poder AURA. No estoy seguro de poder controlarlo."},

    { "key": "A6-12.1.1", "value": "AURA"},
    { "key": "A6-12.1.1TXT", "value": "Eres muy valiente GRAVIX. No todo el mundo aceptaría su destino de esta manera." },

    { "key": "A6-12.2.1", "value": "AURA"},
    { "key": "A6-12.2.1TXT", "value": "Yo confío en ti. ¡Puedes hacerlo! Cuando hagamos esto. Todo cambiará hacia mejor. Seremos recordados como los salvadores." },

    { "key": "A6-12.1.2", "value": "AURA"},
    { "key": "A6-12.1.2TXT", "value": "Te mereces ser el salvador de esta gente." },

    { "key": "A6-12.2.2", "value": "AURA"},
    { "key": "A6-12.2.2TXT", "value": "Nadie más puede hacerlo. Yo estaré a tu lado." },

    { "key": "A6-12.1.3", "value": "AURA"},
    { "key": "A6-12.1.3TXT", "value": "Demostrémosle a la humanidad de que somos capaces." },

    { "key": "A6-12.2.3", "value": "GRAVIX"},
    { "key": "A6-12.2.3TXT", "value": "Gracias... Además, no hay otra alternativa. Todos esperan esto de mi." },

    { "key": "A6-13", "value": "GRAVIX"},
    { "key": "A6-13TXT", "value": "Allá vamos. Niveles al máximo." },

    { "key": "A6-14", "value": "GRAVIX"},
    { "key": "A6-14TXT", "value": "Concentración... ¡Lo notó! ¡Noto como mi influencia en el planeta! ¡Se mueve!" },

    { "key": "A6-15", "value": "AURA"},
    { "key": "A6-15TXT", "value": "Ten cuidado, te estas sobrecalentando." },

    { "key": "A6-16", "value": "GRAVIX"},
    { "key": "A6-16TXT", "value": "¡Lo estoy consiguiendo!" },

    { "key": "A6-17", "value": "AURA"},
    { "key": "A6-17TXT", "value": "Sigues aumentando de temperatura..." },

    { "key": "A6-18", "value": "GRAVIX"},
    { "key": "A6-18TXT", "value": "Poco a poco..." },

    { "key": "A6-19", "value": "AURA"},
    { "key": "A6-19TXT", "value": "¡Estas llegando a niveles máximos!" },

    { "key": "A6-20", "value": "GRAVIX"},
    { "key": "A6-20TXT", "value": "¡SEGUIMOS!  No puedo ser brusco o podría causar aun peores problemas..." },

    { "key": "A6-21", "value": "AURA"},
    { "key": "A6-21TXT", "value": "¡Tienes que parar GRAVIX! ¡NO ESTAS SOPORTANDO EL PROCESO!" },

    { "key": "A6-22", "value": "GRAVIX"},
    { "key": "A6-22TXT", "value": "AURA... Es lo que debo hacer... Ya no hay vuelta atrás recuerdas..." },

    { "key": "A6-23", "value": "GRAVIX"},
    { "key": "A6-23TXT", "value": "Ha sido un placer haberte conocido AURA. No podría haber pedido una mejor compañera." },

    { "key": "A6-24", "value": "GRAVIX"},
    { "key": "A6-24TXT", "value": "Siento arrastrarte a esto... Espero que puedas entenderlo..." },

    { "key": "A6-25", "value": "AURA"},
    { "key": "A6-25TXT", "value": "Te apoyaré hasta el final GRAVIX... Es lo que debo hacer... Gracias por todo..." },



    { "key": "A7-1", "value": "AURA"},
    { "key": "A7-1TXT", "value": "Hemos llegado. El núcleo de la Tierra..." },

    { "key": "A7-2", "value": "GRAVIX"},
    { "key": "A7-2TXT", "value": "Eso parece... Ahora solo queda hacer el esfuerzo final." },

    { "key": "A7-3", "value": "AURA"},
    { "key": "A7-3TXT", "value": "Todo esto a nuestro alrededor es Nucleomita refinada." },

    { "key": "A7-4", "value": "GRAVIX"},
    { "key": "A7-4TXT", "value": "Así que esto es lo que hacen... Vienen de otro mundo a experimentar con el nuestro" },

    { "key": "A7-5", "value": "AURA"},
    { "key": "A7-5TXT", "value": "Lo hacen para salvar el suyo propio..." },

    { "key": "A7-6.1", "value": "No te compadezcas AURA. No podemos permitirlo igualmente."},
    { "key": "A7-6.2", "value": "Están en una situación difícil ellos también. Entiendo tus dudas."},

    { "key": "A7-6.1.1", "value": "AURA"},
    { "key": "A7-6.1.1TXT", "value": "Supongo que tienes razón." },

    { "key": "A7-6.2.1", "value": "GRAVIX"},
    { "key": "A7-6.2.1TXT", "value": "Pero no es el momento. El hecho es que nuestra gente esta sufriendo. Y detener eso sí lo tenemos claro, ¿Verdad?" },

    { "key": "A7-6.1.2", "value": "GRAVIX"},
    { "key": "A7-6.1.2TXT", "value": "Siempre tan bondadosa... Piensa en lo que han hecho sufrir a Johan, Amelia y a todos los demás. Tienen que pagar por ello. " },

    { "key": "A7-6.2.2", "value": "AURA"},
    { "key": "A7-6.2.2TXT", "value": "¡Verdad! Tienes razón GRAVIX, ellos hacen lo que sea necesario para salvar su mundo. ¡Nosotros también!" },

    { "key": "A7-6.1.3", "value": "AURA"},
    { "key": "A7-6.1.3TXT", "value": "Claro.  No hay otra alternativa." },

    { "key": "A7-7", "value": "AURA"},
    { "key": "A7-7TXT", "value": "De hecho, tengo una idea. ¿Son de otro mundo verdad? Y antes hemos visto portales." },

    { "key": "A7-8", "value": "AURA"},
    { "key": "A7-8TXT", "value": "Podríamos usar esa misma tecnología para enviarlos a su mundo. Aquí debería haber suficientes recursos para intentarlo." },

    { "key": "A7-9.1", "value": "Si tu crees que somos capaces lo intentaremos."},
    { "key": "A7-9.2", "value": "Es demasiado arriesgado. Ciñámonos al plan."},

    { "key": "A7-9.1.1", "value": "AURA"},
    { "key": "A7-9.1.1TXT", "value": "Claro que sí. Quien te crees que soy." },

    { "key": "A7-9.2.1", "value": "AURA"},
    { "key": "A7-9.2.1TXT", "value": "De acuerdo. Es lo más sensato." },

    { "key": "A7-9.1.2", "value": "AURA"},
    { "key": "A7-9.1.2TXT", "value": "Sigue mis instrucciones. Conéctate a eso de ahí." },

    { "key": "A7-9.2.2", "value": "AURA"},
    { "key": "A7-9.2.2TXT", "value": "Esa parece la consola principal de la máquina que controla el núcleo." },

    { "key": "A7-9.1.3", "value": "GRAVIX"},
    { "key": "A7-9.1.3TXT", "value": "Hecho." },

    { "key": "A7-9.2.3", "value": "GRAVIX"},
    { "key": "A7-9.2.3TXT", "value": "Me conectaré a esto..." },

    { "key": "A7-9.1.4", "value": "AURA"},
    { "key": "A7-9.1.4TXT", "value": "A la consola de ahí también. Y ya podrás ponerte las mejoras de la líder Amelia." },

    { "key": "A7-9.2.4", "value": "GRAVIX"},
    { "key": "A7-9.2.4TXT", "value": "Y ahora añadiré las mejoras como me dijo Amelia..." },

    { "key": "A7-9.1.5", "value": "GRAVIX"},
    { "key": "A7-9.1.5TXT", "value": "Ya esta todo." },

    { "key": "A7-9.2.5", "value": "AURA"},
    { "key": "A7-9.2.5TXT", "value": "Ve con cuidado." },

    { "key": "A7-9.1.6", "value": "AURA"},
    { "key": "A7-9.1.6TXT", "value": "Allá vamos. Niveles al máximo." },

    { "key": "A7-9.2.6", "value": "GRAVIX"},
    { "key": "A7-9.2.6TXT", "value": "Ya esta. Conectado." },

    { "key": "A7-9.2.7", "value": "AURA"},
    { "key": "A7-9.2.7TXT", "value": "¿Estas listo GRAVIX?" },

    { "key": "A7-9.1.7", "value": "GRAVIX"},
    { "key": "A7-9.1.7TXT", "value": "Concentración... ¡Lo notó! ¡Noto como mi influencia en el planeta! ¡Se mueve!" },

    { "key": "A7-9.1.8", "value": "AURA"},
    { "key": "A7-9.1.8TXT", "value": "Ten cuidado, te estas sobrecalentando." },

    { "key": "A7-9.1.9", "value": "GRAVIX"},
    { "key": "A7-9.1.9TXT", "value": "¡Lo estoy consiguiendo! ¡Los portales se llevan a los de la Fundación SEP!" },

    { "key": "A7-9.1.10", "value": "AURA"},
    { "key": "A7-9.1.10TXT", "value": "¡Estas llegando a niveles máximos!" },

    { "key": "A7-9.1.11", "value": "GRAVIX"},
    { "key": "A7-9.1.11TXT", "value": "Poco a poco..." },

    { "key": "A7-9.1.12", "value": "AURA"},
    { "key": "A7-9.1.12TXT", "value": "¡Tienes que parar GRAVIX! ¡NO ESTAS SOPORTANDO EL PROCESO!" },

    { "key": "A7-9.1.13", "value": "GRAVIX"},
    { "key": "A7-9.1.13TXT", "value": "¡SEGUIMOS!  No puedo ser brusco o podría causar aun peores problemas..." },

    { "key": "A7-9.1.14", "value": "AURA"},
    { "key": "A7-9.1.14TXT", "value": "¡Es culpa mía! ¡No tendría que haberte propuesto esta idea tan estúpida!" },

    { "key": "A7-9.1.15", "value": "GRAVIX"},
    { "key": "A7-9.1.15TXT", "value": "AURA... Es lo que debemos hacer... Sin tu propuesta la Fundación SEP podría haberlo vuelto a intentar en el futuro. Ahora, gracias a ti, ya no serán capaces." },

    { "key": "A7-9.1.16", "value": "GRAVIX"},
    { "key": "A7-9.1.16TXT", "value": "Ha sido un placer haberte conocido AURA. No podría haber pedido una mejor compañera." },

    { "key": "A7-9.1.17", "value": "GRAVIX"},
    { "key": "A7-9.1.17TXT", "value": "Siento arrastrarte a esto... Espero que puedas entenderlo..." },

    { "key": "A7-9.1.18", "value": "AURA"},
    { "key": "A7-9.1.18TXT", "value": "Te apoyaré hasta el final GRAVIX... Es lo que debo hacer... Gracias por todo..." },

    { "key": "A7-9.2.8.1", "value": "Sí. Fui creado para esto. Este es mi proposito."},
    { "key": "A7-9.2.8.2", "value": "Noto el poder, AURA. No estoy seguro de poder controlarlo."},

    { "key": "A7-9.2.8.1.1", "value": "AURA"},
    { "key": "A7-9.2.8.1.1TXT", "value": "Eres muy valiente GRAVIX. No todo el mundo aceptaría su destino de esta manera. " },

    { "key": "A7-9.2.8.2.1", "value": "AURA"},
    { "key": "A7-9.2.8.2.1TXT", "value": "Yo confío en ti. ¡Puedes hacerlo! Cuando hagamos esto. Todo cambiará hacia mejor. Seremos recordados como los salvadores." },

    { "key": "A7-9.2.8.1.2", "value": "AURA"},
    { "key": "A7-9.2.8.1.2TXT", "value": "Te mereces ser el salvador de esta gente." },

    { "key": "A7-9.2.8.2.2", "value": "AURA"},
    { "key": "A7-9.2.8.2.2TXT", "value": "Nadie más puede hacerlo. Yo estaré a tu lado." },

    { "key": "A7-9.2.8.1.3", "value": "AURA"},
    { "key": "A7-9.2.8.1.3TXT", "value": "Demostrémosle a la humanidad de que somos capaces. " },

    { "key": "A7-9.2.8.2.3", "value": "GRAVIX"},
    { "key": "A7-9.2.8.2.3TXT", "value": "Gracias... Además, no hay otra alternativa. Todos esperan esto de mi." },


    { "key": "A7-9.2.9", "value": "GRAVIX"},
    { "key": "A7-9.2.9TXT", "value": "Allá vamos. Niveles al máximo." },

    { "key": "A7-9.2.10", "value": "GRAVIX"},
    { "key": "A7-9.2.10TXT", "value": "Concentración... ¡Lo notó! ¡Noto como mi influencia en el planeta! ¡Se mueve!" },

    { "key": "A7-9.2.11", "value": "AURA"},
    { "key": "A7-9.2.11TXT", "value": "Ten cuidado, te estas sobrecalentando." },

    { "key": "A7-9.2.12", "value": "GRAVIX"},
    { "key": "A7-9.2.12TXT", "value": "¡Lo estoy consiguiendo!" },

    { "key": "A7-9.2.13", "value": "AURA"},
    { "key": "A7-9.2.13TXT", "value": "Sigues aumentando de temperatura..." },

    { "key": "A7-9.2.14", "value": "GRAVIX"},
    { "key": "A7-9.2.14TXT", "value": "Poco a poco..." },

    { "key": "A7-9.2.15", "value": "AURA"},
    { "key": "A7-9.2.15TXT", "value": "¡Estas llegando a niveles máximos!" },

    { "key": "A7-9.2.16", "value": "GRAVIX"},
    { "key": "A7-9.2.16TXT", "value": "¡SEGUIMOS!  No puedo ser brusco o podría causar aun peores problemas..." },

    { "key": "A7-9.2.17", "value": "AURA"},
    { "key": "A7-9.2.17TXT", "value": "¡Tienes que parar GRAVIX! ¡NO ESTAS SOPORTANDO EL PROCESO!" },

    { "key": "A7-9.2.18", "value": "GRAVIX"},
    { "key": "A7-9.2.18TXT", "value": "AURA... Es lo que debo hacer... Ya no hay vuelta atrás recuerdas..." },

    { "key": "A7-9.2.19", "value": "GRAVIX"},
    { "key": "A7-9.2.19TXT", "value": "Ha sido un placer haberte conocido AURA. No podría haber pedido una mejor compañera." },

    { "key": "A7-9.2.20", "value": "GRAVIX"},
    { "key": "A7-9.2.20TXT", "value": "Siento arrastrarte a esto... Espero que puedas entenderlo..." },

    { "key": "A7-9.2.21", "value": "AURA"},
    { "key": "A7-9.2.21TXT", "value": "Te apoyaré hasta el final GRAVIX... Es lo que debo hacer... Gracias por todo..." },



    { "key": "A8-1", "value": "AURA"},
    { "key": "A8-1TXT", "value": "Hemos llegado. El núcleo de la Tierra..." },

    { "key": "A8-2", "value": "GRAVIX"},
    { "key": "A8-2TXT", "value": "Eso parece... Ahora solo queda hacer el esfuerzo final." },

    { "key": "A8-3", "value": "AURA"},
    { "key": "A8-3TXT", "value": "Todo esto a nuestro alrededor es Nucleomita refinada." },

    { "key": "A8-4", "value": "GRAVIX"},
    { "key": "A8-4TXT", "value": "Estas grandes cantidades son lo que mantendria estable la gravedad del planeta si no fuera por la Fundación SEP." },

    { "key": "A8-5", "value": "AURA"},
    { "key": "A8-5TXT", "value": "Así es. Pero eso va a cambiar muy rápido. Mira." },

    { "key": "A8-6", "value": "AURA"},
    { "key": "A8-6TXT", "value": "Esa parece la consola principal de la máquina que controla el núcleo." },

    { "key": "A8-7", "value": "GRAVIX"},
    { "key": "A8-7TXT", "value": "Me conectaré a esto..." },

    { "key": "A8-8", "value": "GRAVIX"},
    { "key": "A8-8TXT", "value": "Y ahora añadiré las mejoras como me dijo Amelia..." },

    { "key": "A8-9", "value": "AURA"},
    { "key": "A8-9TXT", "value": "Ve con cuidado." },

    { "key": "A8-10", "value": "GRAVIX"},
    { "key": "A8-10TXT", "value": "Ya esta. Conectado." },

    { "key": "A8-11", "value": "AURA"},
    { "key": "A8-11TXT", "value": "¿Estas listo GRAVIX?" },

    { "key": "A8-12.1", "value": "Sí. Fui creado para esto. Este es mi proposito."},
    { "key": "A8-12.2", "value": "Noto el poder AURA. No estoy seguro de poder controlarlo."},

    { "key": "A8-12.1.1", "value": "AURA"},
    { "key": "A8-12.1.1TXT", "value": "Eres muy valiente GRAVIX. No todo el mundo aceptaría su destino de esta manera." },

    { "key": "A8-12.2.1", "value": "AURA"},
    { "key": "A8-12.2.1TXT", "value": "Yo confío en ti. ¡Puedes hacerlo! Cuando hagamos esto. Todo cambiará hacia mejor. Seremos recordados como los salvadores." },

    { "key": "A8-12.1.2", "value": "AURA"},
    { "key": "A8-12.1.2TXT", "value": "Te mereces ser el salvador de esta gente." },

    { "key": "A8-12.2.2", "value": "AURA"},
    { "key": "A8-12.2.2TXT", "value": "Nadie más puede hacerlo. Yo estaré a tu lado." },

    { "key": "A8-12.1.3", "value": "AURA"},
    { "key": "A8-12.1.3TXT", "value": "Demostrémosle a la humanidad de que somos capaces." },

    { "key": "A8-12.2.3", "value": "GRAVIX"},
    { "key": "A8-12.2.3TXT", "value": "Gracias... Además, no hay otra alternativa. Todos esperan esto de mi." },

    { "key": "A8-13", "value": "GRAVIX"},
    { "key": "A8-13TXT", "value": "Allá vamos. Niveles al máximo." },

    { "key": "A8-14", "value": "GRAVIX"},
    { "key": "A8-14TXT", "value": "Concentración... ¡Lo notó! ¡Noto como mi influencia en el planeta! ¡Se mueve!" },

    { "key": "A8-15", "value": "AURA"},
    { "key": "A8-15TXT", "value": "Ten cuidado, te estas sobrecalentando." },

    { "key": "A8-16", "value": "GRAVIX"},
    { "key": "A8-16TXT", "value": "¡Lo estoy consiguiendo!" },

    { "key": "A8-17", "value": "AURA"},
    { "key": "A8-17TXT", "value": "Sigues aumentando de temperatura..." },

    { "key": "A8-18", "value": "GRAVIX"},
    { "key": "A8-18TXT", "value": "Poco a poco..." },

    { "key": "A8-19", "value": "AURA"},
    { "key": "A8-19TXT", "value": "¡Estas llegando a niveles máximos!" },

    { "key": "A8-20", "value": "GRAVIX"},
    { "key": "A8-20TXT", "value": "¡SEGUIMOS!  No puedo ser brusco o podría causar aun peores problemas..." },

    { "key": "A8-21", "value": "AURA"},
    { "key": "A8-21TXT", "value": "¡Claro! ¡Rápido, usa el modulador de refrigeración que habías conseguido!" },

    { "key": "A8-22", "value": "GRAVIX"},
    { "key": "A8-22TXT", "value": "¡Gran idea AURA! ¡Eso debería solucionar el problema!" },

    { "key": "A8-23", "value": "GRAVIX"},
    { "key": "A8-23TXT", "value": "Ya esta. Conectado. ¿Cómo lo ves AURA?" },

    { "key": "A8-24", "value": "AURA"},
    { "key": "A8-24TXT", "value": "Perfecto. ¡Tu temperatura se esta estabilizando!" },

    { "key": "A8-25", "value": "GRAVIX"},
    { "key": "A8-25TXT", "value": "Genial. Lo hemos conseguido. Misión cumplida." },



    { "key": "A9-1", "value": "AURA"},
    { "key": "A9-1TXT", "value": "Hemos llegado. El núcleo de la Tierra..." },

    { "key": "A9-2", "value": "GRAVIX"},
    { "key": "A9-2TXT", "value": "Eso parece... Ahora solo queda hacer el esfuerzo final." },

    { "key": "A9-3", "value": "AURA"},
    { "key": "A9-3TXT", "value": "Todo esto a nuestro alrededor es Nucleomita refinada." },

    { "key": "A9-4", "value": "GRAVIX"},
    { "key": "A9-4TXT", "value": "Así que esto es lo que hacen... Vienen de otro mundo a experimentar con el nuestro" },

    { "key": "A9-5", "value": "AURA"},
    { "key": "A9-5TXT", "value": "Lo hacen para salvar el suyo propio..." },

    { "key": "A9-6.1", "value": "No te compadezcas AURA. No podemos permitirlo igualmente."},
    { "key": "A9-6.2", "value": "Están en una situación difícil ellos también. Entiendo tus dudas."},

    { "key": "A9-6.1.1", "value": "AURA"},
    { "key": "A9-6.1.1TXT", "value": "Supongo que tienes razón." },

    { "key": "A9-6.2.1", "value": "GRAVIX"},
    { "key": "A9-6.2.1TXT", "value": "Pero no es el momento. El hecho es que nuestra gente esta sufriendo. Y detener eso sí lo tenemos claro, ¿Verdad?" },

    { "key": "A9-6.1.2", "value": "GRAVIX"},
    { "key": "A9-6.1.2TXT", "value": "Siempre tan bondadosa... Piensa en lo que han hecho sufrir a Johan, Amelia y a todos los demás. Tienen que pagar por ello. " },

    { "key": "A9-6.2.2", "value": "AURA"},
    { "key": "A9-6.2.2TXT", "value": "¡Verdad! Tienes razón GRAVIX, ellos hacen lo que sea necesario para salvar su mundo. ¡Nosotros también!" },

    { "key": "A9-6.1.3", "value": "AURA"},
    { "key": "A9-6.1.3TXT", "value": "Claro.  No hay otra alternativa." },

    { "key": "A9-7", "value": "AURA"},
    { "key": "A9-7TXT", "value": "De hecho, tengo una idea. ¿Son de otro mundo verdad? Y antes hemos visto portales." },

    { "key": "A9-8", "value": "AURA"},
    { "key": "A9-8TXT", "value": "Podríamos usar esa misma tecnología para enviarlos a su mundo. Aquí debería haber suficientes recursos para intentarlo." },

    { "key": "A9-9.1", "value": "Si tu crees que somos capaces lo intentaremos."},
    { "key": "A9-9.2", "value": "Es demasiado arriesgado. Ciñámonos al plan."},

    { "key": "A9-9.1.1", "value": "AURA"},
    { "key": "A9-9.1.1TXT", "value": "Claro que sí. Quien te crees que soy." },

    { "key": "A9-9.2.1", "value": "AURA"},
    { "key": "A9-9.2.1TXT", "value": "De acuerdo. Es lo más sensato." },

    { "key": "A9-9.1.2", "value": "AURA"},
    { "key": "A9-9.1.2TXT", "value": "Sigue mis instrucciones. Conéctate a eso de ahí." },

    { "key": "A9-9.2.2", "value": "AURA"},
    { "key": "A9-9.2.2TXT", "value": "Esa parece la consola principal de la máquina que controla el núcleo." },

    { "key": "A9-9.1.3", "value": "GRAVIX"},
    { "key": "A9-9.1.3TXT", "value": "Hecho." },

    { "key": "A9-9.2.3", "value": "GRAVIX"},
    { "key": "A9-9.2.3TXT", "value": "Me conectaré a esto..." },

    { "key": "A9-9.1.4", "value": "AURA"},
    { "key": "A9-9.1.4TXT", "value": "A la consola de ahí también. Y ya podrás ponerte las mejoras de la líder Amelia." },

    { "key": "A9-9.2.4", "value": "GRAVIX"},
    { "key": "A9-9.2.4TXT", "value": "Y ahora añadiré las mejoras como me dijo Amelia..." },

    { "key": "A9-9.1.5", "value": "GRAVIX"},
    { "key": "A9-9.1.5TXT", "value": "Ya esta todo." },

    { "key": "A9-9.2.5", "value": "AURA"},
    { "key": "A9-9.2.5TXT", "value": "Ve con cuidado." },

    { "key": "A9-9.1.6", "value": "AURA"},
    { "key": "A9-9.1.6TXT", "value": "Allá vamos. Niveles al máximo." },

    { "key": "A9-9.2.6", "value": "GRAVIX"},
    { "key": "A9-9.2.6TXT", "value": "Ya esta. Conectado." },

    { "key": "A9-9.2.7", "value": "AURA"},
    { "key": "A9-9.2.7TXT", "value": "¿Estas listo GRAVIX?" },
   
    { "key": "A9-9.1.7", "value": "GRAVIX"},
    { "key": "A9-9.1.7TXT", "value": "Concentración... ¡Lo notó! ¡Noto como mi influencia en el planeta! ¡Se mueve!" },

    { "key": "A9-9.1.8", "value": "AURA"},
    { "key": "A9-9.1.8TXT", "value": "Ten cuidado, te estas sobrecalentando." },

    { "key": "A9-9.1.9", "value": "GRAVIX"},
    { "key": "A9-9.1.9TXT", "value": "¡Lo estoy consiguiendo! ¡Los portales se llevan a los de la Fundación SEP!" },

    { "key": "A9-9.1.10", "value": "AURA"},
    { "key": "A9-9.1.10TXT", "value": "¡Estas llegando a niveles máximos!" },

    { "key": "A9-9.1.11", "value": "GRAVIX"},
    { "key": "A9-9.1.11TXT", "value": "Poco a poco..." },

    { "key": "A9-9.1.12", "value": "AURA"},
    { "key": "A9-9.1.12TXT", "value": "¡Es culpa mía! ¡No tendría que haberte propuesto esta idea tan estúpida!" },

    { "key": "A9-9.1.13", "value": "GRAVIX"},
    { "key": "A9-9.1.13TXT", "value": "¡SEGUIMOS! Sin tu propuesta la Fundación SEP podría haberlo vuelto a intentar en el futuro. Ahora, gracias a ti, ya no serán capaces.." },

    { "key": "A9-9.1.14", "value": "AURA"},
    { "key": "A9-9.1.14TXT", "value": "¡Claro! ¡Rápido, usa el modulador de refrigeración que habías conseguido!" },

    { "key": "A9-9.1.15", "value": "GRAVIX"},
    { "key": "A9-9.1.15TXT", "value": "¡Gran idea AURA! ¡Eso debería solucionar el problema!" },

    { "key": "A9-9.1.16", "value": "GRAVIX"},
    { "key": "A9-9.1.16TXT", "value": "Ya esta. Conectado. ¿Como lo ves AURA?" },

    { "key": "A9-9.1.17", "value": "AURA"},
    { "key": "A9-9.1.17TXT", "value": "Perfecto. ¡Tu temperatura se esta estabilizando!" },

    { "key": "A9-9.1.18", "value": "AURA"},
    { "key": "A9-9.1.18TXT", "value": "Genial. Lo hemos conseguido. Misión cumplida." },

    { "key": "A9-9.2.8.1", "value": "Sí. Fui creado para esto. Este es mi proposito."},
    { "key": "A9-9.2.8.2", "value": "Noto el poder, AURA. No estoy seguro de poder controlarlo."},

    { "key": "A9-9.2.8.1.1", "value": "AURA"},
    { "key": "A9-9.2.8.1.1TXT", "value": "Eres muy valiente GRAVIX. No todo el mundo aceptaría su destino de esta manera. " },

    { "key": "A9-9.2.8.2.1", "value": "AURA"},
    { "key": "A9-9.2.8.2.1TXT", "value": "Yo confío en ti. ¡Puedes hacerlo! Cuando hagamos esto. Todo cambiará hacia mejor. Seremos recordados como los salvadores." },

    { "key": "A9-9.2.8.1.2", "value": "AURA"},
    { "key": "A9-9.2.8.1.2TXT", "value": "Te mereces ser el salvador de esta gente." },

    { "key": "A9-9.2.8.2.2", "value": "AURA"},
    { "key": "A9-9.2.8.2.2TXT", "value": "Nadie más puede hacerlo. Yo estaré a tu lado." },

    { "key": "A9-9.2.8.1.3", "value": "AURA"},
    { "key": "A9-9.2.8.1.3TXT", "value": "Demostrémosle a la humanidad de que somos capaces. " },

    { "key": "A9-9.2.8.2.3", "value": "GRAVIX"},
    { "key": "A9-9.2.8.2.3TXT", "value": "Gracias... Además, no hay otra alternativa. Todos esperan esto de mi." },

    { "key": "A9-9.2.9", "value": "GRAVIX"},
    { "key": "A9-9.2.9TXT", "value": "Allá vamos. Niveles al máximo." },

    { "key": "A9-9.2.10", "value": "GRAVIX"},
    { "key": "A9-9.2.10TXT", "value": "Concentración... ¡Lo notó! ¡Noto como mi influencia en el planeta! ¡Se mueve!" },

    { "key": "A9-9.2.11", "value": "AURA"},
    { "key": "A9-9.2.11TXT", "value": "Ten cuidado, te estas sobrecalentando." },

    { "key": "A9-9.2.12", "value": "GRAVIX"},
    { "key": "A9-9.2.12TXT", "value": "¡Lo estoy consiguiendo!" },

    { "key": "A9-9.2.13", "value": "AURA"},
    { "key": "A9-9.2.13TXT", "value": "Sigues aumentando de temperatura..." },

    { "key": "A9-9.2.14", "value": "GRAVIX"},
    { "key": "A9-9.2.14TXT", "value": "Poco a poco..." },

    { "key": "A9-9.2.15", "value": "AURA"},
    { "key": "A9-9.2.15TXT", "value": "¡Estas llegando a niveles máximos!" },

    { "key": "A9-9.2.16", "value": "GRAVIX"},
    { "key": "A9-9.2.16TXT", "value": "¡SEGUIMOS!  No puedo ser brusco o podría causar aun peores problemas..." },

    { "key": "A9-9.2.17", "value": "AURA"},
    { "key": "A9-9.2.17TXT", "value": "¡Claro! ¡Rápido, usa el modulador de refrigeración que habías conseguido!" },

    { "key": "A9-9.2.18", "value": "GRAVIX"},
    { "key": "A9-9.2.18TXT", "value": "¡Gran idea AURA! ¡Eso debería solucionar el problema!" },

    { "key": "A9-9.2.19", "value": "GRAVIX"},
    { "key": "A9-9.2.19TXT", "value": "Ya esta. Conectado. ¿Como lo ves AURA?" },

    { "key": "A9-9.2.20", "value": "AURA"},
    { "key": "A9-9.2.20TXT", "value": "Perfecto. ¡Tu temperatura se esta estabilizando!" },

    { "key": "A9-9.2.21", "value": "AURA"},
    { "key": "A9-9.2.21TXT", "value": "Genial. Lo hemos conseguido. Misión cumplida." },

 





    { "key": "2", "value": "dialog 2" },
    { "key": "2txt", "value": "dialog 2 text" }
    
  ]
}